{
    "Ar36": {
        "error": 0.0002119240158104474,
        "error_type": "",
        "fit": "previous",
        "references": [
            {
                "exclude": false,
                "record_id": "ba-01-A-2938"
            }
        ],
        "value": 0.004336872460581119
    },
    "Ar36L2": {
        "error": 0.007021198135832518,
        "error_type": "",
        "fit": "previous",
        "references": [
            {
                "exclude": false,
                "record_id": "ba-01-A-2938"
            }
        ],
        "value": 0.0027314965328813882
    },
    "Ar37": {
        "error": 0.007932881330617484,
        "error_type": "",
        "fit": "previous",
        "references": [
            {
                "exclude": false,
                "record_id": "ba-01-A-2938"
            }
        ],
        "value": 0.020571917935396707
    },
    "Ar37L1": {
        "error": 0.015898025245691522,
        "error_type": "",
        "fit": "previous",
        "references": [
            {
                "exclude": false,
                "record_id": "ba-01-A-2938"
            }
        ],
        "value": 0.023993336448339606
    },
    "Ar38": {
        "error": 0.016855828735174827,
        "error_type": "",
        "fit": "previous",
        "references": [
            {
                "exclude": false,
                "record_id": "ba-01-A-2938"
            }
        ],
        "value": 0.00435480935917673
    },
    "Ar38AX": {
        "error": 0.007490109551907584,
        "error_type": "",
        "fit": "previous",
        "references": [
            {
                "exclude": false,
                "record_id": "ba-01-A-2938"
            }
        ],
        "value": 0.013923594226601891
    },
    "Ar39": {
        "error": 0.008457061353290071,
        "error_type": "",
        "fit": "previous",
        "references": [
            {
                "exclude": false,
                "record_id": "ba-01-A-2938"
            }
        ],
        "value": 0.037844831608628046
    },
    "Ar39H1": {
        "error": 0.015982974172979388,
        "error_type": "",
        "fit": "previous",
        "references": [
            {
                "exclude": false,
                "record_id": "ba-01-A-2938"
            }
        ],
        "value": 0.02247629475405459
    },
    "Ar40": {
        "error": 0.025211507542247026,
        "error_type": "",
        "fit": "previous",
        "references": [
            {
                "exclude": false,
                "record_id": "ba-01-A-2938"
            }
        ],
        "value": 1.040977147202154
    },
    "Ar40H2": {
        "error": 0.02497191861541697,
        "error_type": "",
        "fit": "previous",
        "references": [
            {
                "exclude": false,
                "record_id": "ba-01-A-2938"
            }
        ],
        "value": 1.012211171314025
    },
    "Ar41": {
        "error": 0.0,
        "error_type": "",
        "fit": "previous",
        "references": [
            {
                "exclude": false,
                "record_id": "ba-01-A-2938"
            }
        ],
        "value": 0.08321461700009607
    }
}