{
    "Ar36": {
        "error": 0.00020380294230619265,
        "error_type": "",
        "fit": "previous",
        "references": [
            {
                "exclude": false,
                "record_id": "ba-01-A-2917"
            }
        ],
        "value": 0.005682816872854739
    },
    "Ar36L2": {
        "error": 0.009757390186274533,
        "error_type": "",
        "fit": "previous",
        "references": [
            {
                "exclude": false,
                "record_id": "ba-01-A-2917"
            }
        ],
        "value": -0.002952384192209166
    },
    "Ar37": {
        "error": 0.006845731826026973,
        "error_type": "",
        "fit": "previous",
        "references": [
            {
                "exclude": false,
                "record_id": "ba-01-A-2917"
            }
        ],
        "value": 0.01402565548752423
    },
    "Ar37L1": {
        "error": 0.01717874414304434,
        "error_type": "",
        "fit": "previous",
        "references": [
            {
                "exclude": false,
                "record_id": "ba-01-A-2917"
            }
        ],
        "value": 0.013999366092842306
    },
    "Ar38": {
        "error": 0.015276242810885982,
        "error_type": "",
        "fit": "previous",
        "references": [
            {
                "exclude": false,
                "record_id": "ba-01-A-2917"
            }
        ],
        "value": -0.018851483842132172
    },
    "Ar38AX": {
        "error": 0.008576277939983272,
        "error_type": "",
        "fit": "previous",
        "references": [
            {
                "exclude": false,
                "record_id": "ba-01-A-2917"
            }
        ],
        "value": 0.011449251235363844
    },
    "Ar39": {
        "error": 0.006984035743140401,
        "error_type": "",
        "fit": "previous",
        "references": [
            {
                "exclude": false,
                "record_id": "ba-01-A-2917"
            }
        ],
        "value": 0.019886987370563068
    },
    "Ar39H1": {
        "error": 0.016018525612845624,
        "error_type": "",
        "fit": "previous",
        "references": [
            {
                "exclude": false,
                "record_id": "ba-01-A-2917"
            }
        ],
        "value": 0.004165829655759248
    },
    "Ar40": {
        "error": 0.027731634779906107,
        "error_type": "",
        "fit": "previous",
        "references": [
            {
                "exclude": false,
                "record_id": "ba-01-A-2917"
            }
        ],
        "value": 1.44481567023873
    },
    "Ar40H2": {
        "error": 0.024950167403561894,
        "error_type": "",
        "fit": "previous",
        "references": [
            {
                "exclude": false,
                "record_id": "ba-01-A-2917"
            }
        ],
        "value": 1.4782249694181133
    },
    "Ar41": {
        "error": 0.0,
        "error_type": "",
        "fit": "previous",
        "references": [
            {
                "exclude": false,
                "record_id": "ba-01-A-2917"
            }
        ],
        "value": 0.09839217948679602
    }
}