{
    "Ar36": {
        "error": 0.0033918700962528854,
        "error_type": null,
        "filter_outliers_dict": {
            "filter_outliers": false,
            "iterations": 1,
            "std_devs": 2
        },
        "fit": "linear",
        "value": 2.6121338513479033
    },
    "Ar36L2": {
        "error": 0.008288708485492602,
        "error_type": null,
        "filter_outliers_dict": {
            "filter_outliers": false,
            "iterations": 1,
            "std_devs": 2
        },
        "fit": "linear",
        "value": 2.637893663270132
    },
    "Ar37": {
        "error": 0.00668353649100854,
        "error_type": null,
        "filter_outliers_dict": {
            "filter_outliers": false,
            "iterations": 1,
            "std_devs": 2
        },
        "fit": "linear",
        "value": 0.03188074498538031
    },
    "Ar37L1": {
        "error": 0.014817036578639657,
        "error_type": null,
        "filter_outliers_dict": {
            "filter_outliers": false,
            "iterations": 1,
            "std_devs": 2
        },
        "fit": "linear",
        "value": 0.034636191961381985
    },
    "Ar38": {
        "error": 0.01631211818577741,
        "error_type": null,
        "filter_outliers_dict": {
            "filter_outliers": false,
            "iterations": 1,
            "std_devs": 2
        },
        "fit": "linear",
        "value": 0.4743795971849285
    },
    "Ar38AX": {
        "error": 0.007497224673422405,
        "error_type": null,
        "filter_outliers_dict": {
            "filter_outliers": false,
            "iterations": 1,
            "std_devs": 2
        },
        "fit": "linear",
        "value": 0.49412059257182955
    },
    "Ar39": {
        "error": 0.008455266009394183,
        "error_type": null,
        "filter_outliers_dict": {
            "filter_outliers": false,
            "iterations": 1,
            "std_devs": 2
        },
        "fit": "linear",
        "value": 0.0725813830988018
    },
    "Ar39H1": {
        "error": 0.015631732062360158,
        "error_type": null,
        "filter_outliers_dict": {
            "filter_outliers": false,
            "iterations": 1,
            "std_devs": 2
        },
        "fit": "linear",
        "value": 0.00989048542878429
    },
    "Ar40": {
        "error": 0.07199833322693511,
        "error_type": null,
        "filter_outliers_dict": {
            "filter_outliers": false,
            "iterations": 1,
            "std_devs": 2
        },
        "fit": "parabolic",
        "value": 784.9720415352813
    },
    "Ar40H2": {
        "error": 0.06137787651410157,
        "error_type": null,
        "filter_outliers_dict": {
            "filter_outliers": false,
            "iterations": 1,
            "std_devs": 2
        },
        "fit": "parabolic",
        "value": 784.9170711791979
    },
    "Ar41": {
        "error": 0.0,
        "error_type": null,
        "filter_outliers_dict": {
            "filter_outliers": false,
            "iterations": 1,
            "std_devs": 2
        },
        "fit": "linear",
        "value": 0.0
    }
}